ubo_bindings/__init__.py
ubo_bindings/client.py
ubo_bindings/package_info/__init__.py
ubo_bindings/package_info/v1/__init__.py
ubo_bindings/secrets/__init__.py
ubo_bindings/secrets/v1/__init__.py
ubo_bindings/store/__init__.py
ubo_bindings/store/v1/__init__.py
ubo_bindings/ubo/__init__.py
ubo_bindings/ubo/v1/__init__.py
ubo_app_raw_bindings-1.6.0.dist-info/METADATA
ubo_app_raw_bindings-1.6.0.dist-info/WHEEL
ubo_app_raw_bindings-1.6.0.dist-info/RECORD
