Metadata-Version: 2.4
Name: ubo-app-raw-bindings
Version: 1.6.0
Summary: Raw bindings for UBO App.
Author-email: Sassan Haradji <me@sassanh.com>
Maintainer-email: Sassan Haradji <me@sassanh.com>
License-Expression: Apache-2.0
Keywords: bindings,grpc,home assistance,python,raspberry pi,rpi,ubo,ubo-pod
Requires-Python: <3.12,>=3.11
Requires-Dist: betterproto[compiler]==2.0.0b7
